MANIFEST.in
README.rst
TODO.md
setup.py
collective/__init__.py
collective.signupsheet.egg-info/PKG-INFO
collective.signupsheet.egg-info/SOURCES.txt
collective.signupsheet.egg-info/dependency_links.txt
collective.signupsheet.egg-info/entry_points.txt
collective.signupsheet.egg-info/namespace_packages.txt
collective.signupsheet.egg-info/not-zip-safe
collective.signupsheet.egg-info/requires.txt
collective.signupsheet.egg-info/top_level.txt
collective/signupsheet/__init__.py
collective/signupsheet/config.py
collective/signupsheet/configure.zcml
collective/signupsheet/interfaces.py
collective/signupsheet/permissions.zcml
collective/signupsheet/setuphandlers.py
collective/signupsheet/Extensions/Install.py
collective/signupsheet/adapters/__init__.py
collective/signupsheet/adapters/configure.zcml
collective/signupsheet/adapters/initialize_signup_sheet_form.py
collective/signupsheet/browsers/__init__.py
collective/signupsheet/browsers/configure.zcml
collective/signupsheet/browsers/import_registrants.pt
collective/signupsheet/browsers/pfg_field_messages.py
collective/signupsheet/browsers/pfg_utilities.py
collective/signupsheet/browsers/quickedit.pt
collective/signupsheet/browsers/registrants_data.py
collective/signupsheet/browsers/registrants_data_export.pt
collective/signupsheet/browsers/registrants_notification.pt
collective/signupsheet/browsers/registrants_notification.py
collective/signupsheet/browsers/signupsheet_baseview.py
collective/signupsheet/browsers/view_registrants.pt
collective/signupsheet/browsers/resources/confirm_icon.png
collective/signupsheet/browsers/resources/delete_icon.png
collective/signupsheet/browsers/resources/edit.png
collective/signupsheet/browsers/resources/hourglass.png
collective/signupsheet/browsers/resources/question.png
collective/signupsheet/browsers/resources/signupsheet.css
collective/signupsheet/browsers/resources/signupsheet.js
collective/signupsheet/contents/__init__.py
collective/signupsheet/contents/configure.zcml
collective/signupsheet/contents/signupsheet.py
collective/signupsheet/events/__init__.py
collective/signupsheet/events/configure.zcml
collective/signupsheet/events/finalize_registrant.py
collective/signupsheet/events/signupsheet_events.py
collective/signupsheet/locales/collective.signupsheet-manual.pot
collective/signupsheet/locales/collective.signupsheet.pot
