Metadata-Version: 1.1
Name: collective.signupsheet
Version: 0.3.2
Summary: A Plone solution for manage signup attendance to events
Home-page: http://plone.org/products/collective.signupsheet
Author: RedTurtle Technology
Author-email: sviluppoplone@redturtle.it
License: GPL
Keywords: signupsheet plone plonegov ploneformgen event subscription
Platform: UNKNOWN
Classifier: Framework :: Plone
Classifier: Framework :: Plone :: 4.2
Classifier: Framework :: Plone :: 4.3
Classifier: Programming Language :: Python
